{
  "portrait_core_available": false,
  "warnings": [
    "portrait_core недоступен, использована базовая OpenCV-оценка"
  ],
  "metadata": {
    "frame_index": 41050,
    "timestamp_seconds": 1642.0,
    "source_frame_size": [
      640,
      360
    ],
    "box": [
      261,
      44,
      108,
      108
    ]
  },
  "quality": 1.0,
  "opencv_metrics": {
    "blur_score": 564.95752570068,
    "width": 162,
    "height": 162
  },
  "dataset_builder": {
    "status": "warning",
    "warnings": [
      "portrait_core недоступен, использована базовая OpenCV-оценка"
    ],
    "rejection_reasons": []
  }
}