{
  "portrait_core_available": false,
  "warnings": [
    "portrait_core недоступен, использована базовая OpenCV-оценка"
  ],
  "metadata": {
    "frame_index": 36600,
    "timestamp_seconds": 1464.0,
    "source_frame_size": [
      640,
      360
    ],
    "box": [
      319,
      68,
      54,
      54
    ]
  },
  "quality": 1.0,
  "opencv_metrics": {
    "blur_score": 3287.3863417724615,
    "width": 80,
    "height": 80
  },
  "dataset_builder": {
    "status": "rejected",
    "warnings": [
      "portrait_core недоступен, использована базовая OpenCV-оценка"
    ],
    "rejection_reasons": [
      "лицо слишком маленькое"
    ]
  }
}