{
  "portrait_core_available": false,
  "warnings": [
    "portrait_core недоступен, использована базовая OpenCV-оценка"
  ],
  "metadata": {
    "frame_index": 31800,
    "timestamp_seconds": 1272.0,
    "source_frame_size": [
      640,
      360
    ],
    "box": [
      289,
      77,
      108,
      108
    ]
  },
  "quality": 0.7263298797485646,
  "opencv_metrics": {
    "blur_score": 101.68618316479903,
    "width": 162,
    "height": 162
  },
  "dataset_builder": {
    "status": "warning",
    "warnings": [
      "portrait_core недоступен, использована базовая OpenCV-оценка"
    ],
    "rejection_reasons": []
  }
}