{
  "portrait_core_available": false,
  "warnings": [
    "portrait_core недоступен, использована базовая OpenCV-оценка"
  ],
  "metadata": {
    "frame_index": 54150,
    "timestamp_seconds": 2166.0,
    "source_frame_size": [
      640,
      360
    ],
    "box": [
      282,
      61,
      71,
      71
    ]
  },
  "quality": 1.0,
  "opencv_metrics": {
    "blur_score": 434.9286963024666,
    "width": 105,
    "height": 105
  },
  "dataset_builder": {
    "status": "warning",
    "warnings": [
      "portrait_core недоступен, использована базовая OpenCV-оценка"
    ],
    "rejection_reasons": []
  }
}