{
  "portrait_core_available": false,
  "warnings": [
    "portrait_core недоступен, использована базовая OpenCV-оценка"
  ],
  "metadata": {
    "frame_index": 83700,
    "timestamp_seconds": 3348.0,
    "source_frame_size": [
      640,
      360
    ],
    "box": [
      293,
      50,
      69,
      69
    ]
  },
  "quality": 1.0,
  "opencv_metrics": {
    "blur_score": 379.08935609309003,
    "width": 103,
    "height": 103
  },
  "dataset_builder": {
    "status": "warning",
    "warnings": [
      "portrait_core недоступен, использована базовая OpenCV-оценка"
    ],
    "rejection_reasons": []
  }
}