{
  "portrait_core_available": false,
  "warnings": [
    "portrait_core недоступен, использована базовая OpenCV-оценка"
  ],
  "metadata": {
    "frame_index": 41750,
    "timestamp_seconds": 1670.0,
    "source_frame_size": [
      640,
      360
    ],
    "box": [
      282,
      68,
      72,
      72
    ]
  },
  "quality": 1.0,
  "opencv_metrics": {
    "blur_score": 371.25776473040986,
    "width": 108,
    "height": 108
  },
  "dataset_builder": {
    "status": "warning",
    "warnings": [
      "portrait_core недоступен, использована базовая OpenCV-оценка"
    ],
    "rejection_reasons": []
  }
}