{
  "portrait_core_available": false,
  "warnings": [
    "portrait_core недоступен, использована базовая OpenCV-оценка"
  ],
  "metadata": {
    "frame_index": 21240,
    "timestamp_seconds": 885.0,
    "source_frame_size": [
      640,
      360
    ],
    "box": [
      295,
      83,
      86,
      86
    ]
  },
  "quality": 1.0,
  "opencv_metrics": {
    "blur_score": 938.375596080053,
    "width": 146,
    "height": 146
  },
  "dataset_builder": {
    "status": "warning",
    "warnings": [
      "portrait_core недоступен, использована базовая OpenCV-оценка"
    ],
    "rejection_reasons": []
  }
}